sctfbridge/CLUB.py
sctfbridge/__init__.py
sctfbridge/model.py
sctfbridge/pathexplainer.py
sctfbridge/utils/__init__.py
sctfbridge/utils/data_processing.py
sctfbridge/utils/loss_function.py
sctfbridge-0.1.1.dist-info/METADATA
sctfbridge-0.1.1.dist-info/WHEEL
sctfbridge-0.1.1.dist-info/top_level.txt
sctfbridge-0.1.1.dist-info/RECORD
