Metadata-Version: 2.2
Name: sctfbridge
Version: 0.1.1
Summary: sctfbridge 
Author: Feng-ao Wang
Requires-Python: >=3.8
Requires-Dist: torch~=2.6.0
Requires-Dist: numpy~=2.2.5
Requires-Dist: scanpy~=1.11.1
Requires-Dist: episcanpy~=0.4.0
Requires-Dist: pandas~=2.3.0
Requires-Dist: pybedtools~=0.12.0
Requires-Dist: anndata~=0.11.4
Requires-Dist: tqdm~=4.67.1
Requires-Dist: setuptools~=75.8.0
Requires-Dist: scipy~=1.15.2
Dynamic: author
Dynamic: requires-dist
Dynamic: requires-python
Dynamic: summary
